omgpt/__init__.py
omgpt/shtool.py
omgpt-0.0.12.dist-info/LICENSE
omgpt-0.0.12.dist-info/METADATA
omgpt-0.0.12.dist-info/WHEEL
omgpt-0.0.12.dist-info/entry_points.txt
omgpt-0.0.12.dist-info/RECORD
