Metadata-Version: 2.1
Name: omgpt
Version: 0.0.12
Summary: Simplify and enhance your command-line experience with the power of AI
Home-page: https://github.com/ywkim/omgpt
License: MIT
Author: Youngwook Kim
Author-email: youngwook.kim@gmail.com
Requires-Python: >=3.8.1,<4.0.0
Classifier: License :: OSI Approved :: MIT License
Classifier: Programming Language :: Python :: 3
Classifier: Programming Language :: Python :: 3.9
Classifier: Programming Language :: Python :: 3.10
Classifier: Programming Language :: Python :: 3.11
Requires-Dist: langchain (>=0.0.205,<0.1.0)
Requires-Dist: openai (>=0.27.8,<0.28.0)
Requires-Dist: prompt-toolkit (>=3.0.39,<4.0.0)
